pydra/tasks/freesurfer/__init__.py
pydra/tasks/freesurfer/_version.py
pydra/tasks/freesurfer/latest.py
pydra/tasks/freesurfer/v8/__init__.py
pydra/tasks/freesurfer/v8/_post_release.py
pydra/tasks/freesurfer/v8/longitudinal/__init__.py
pydra/tasks/freesurfer/v8/longitudinal/fuse_segmentations.py
pydra/tasks/freesurfer/v8/longitudinal/robust_template.py
pydra/tasks/freesurfer/v8/model/__init__.py
pydra/tasks/freesurfer/v8/model/binarize.py
pydra/tasks/freesurfer/v8/model/concatenate.py
pydra/tasks/freesurfer/v8/model/glm_fit.py
pydra/tasks/freesurfer/v8/model/label_2_annot.py
pydra/tasks/freesurfer/v8/model/label_2_label.py
pydra/tasks/freesurfer/v8/model/label_2_vol.py
pydra/tasks/freesurfer/v8/model/mris_preproc.py
pydra/tasks/freesurfer/v8/model/mris_preproc_recon_all.py
pydra/tasks/freesurfer/v8/model/ms__lda.py
pydra/tasks/freesurfer/v8/model/one_sample_t_test.py
pydra/tasks/freesurfer/v8/model/seg_stats.py
pydra/tasks/freesurfer/v8/model/seg_stats_recon_all.py
pydra/tasks/freesurfer/v8/model/spherical_average.py
pydra/tasks/freesurfer/v8/nipype_ports/__init__.py
pydra/tasks/freesurfer/v8/nipype_ports/interfaces/__init__.py
pydra/tasks/freesurfer/v8/nipype_ports/interfaces/io.py
pydra/tasks/freesurfer/v8/nipype_ports/utils/__init__.py
pydra/tasks/freesurfer/v8/nipype_ports/utils/filemanip.py
pydra/tasks/freesurfer/v8/nipype_ports/utils/misc.py
pydra/tasks/freesurfer/v8/petsurfer/__init__.py
pydra/tasks/freesurfer/v8/petsurfer/gtm_seg.py
pydra/tasks/freesurfer/v8/petsurfer/gtmpvc.py
pydra/tasks/freesurfer/v8/petsurfer/logan.py
pydra/tasks/freesurfer/v8/petsurfer/mrtm1.py
pydra/tasks/freesurfer/v8/petsurfer/mrtm2.py
pydra/tasks/freesurfer/v8/preprocess/__init__.py
pydra/tasks/freesurfer/v8/preprocess/apply_vol_transform.py
pydra/tasks/freesurfer/v8/preprocess/bb_register.py
pydra/tasks/freesurfer/v8/preprocess/ca_label.py
pydra/tasks/freesurfer/v8/preprocess/ca_normalize.py
pydra/tasks/freesurfer/v8/preprocess/ca_register.py
pydra_tasks_freesurfer-0.3.0.dist-info/METADATA
pydra_tasks_freesurfer-0.3.0.dist-info/WHEEL
pydra_tasks_freesurfer-0.3.0.dist-info/licenses/LICENSE
pydra_tasks_freesurfer-0.3.0.dist-info/licenses/NOTICE
pydra_tasks_freesurfer-0.3.0.dist-info/RECORD
